business_rules/__init__.py
business_rules/actions.py
business_rules/engine.py
business_rules/fields.py
business_rules/operators.py
business_rules/utils.py
business_rules/variables.py
business_rules-1.1.1.dist-info/LICENSE
business_rules-1.1.1.dist-info/METADATA
business_rules-1.1.1.dist-info/WHEEL
business_rules-1.1.1.dist-info/top_level.txt
business_rules-1.1.1.dist-info/RECORD
