Metadata-Version: 2.1
Name: business-rules
Version: 1.1.1
Summary: Python DSL for setting up business intelligence rules that can be configured without code
Home-page: https://github.com/venmo/business-rules
Author: Venmo
Author-email: open-source@venmo.com
License: MIT
Platform: UNKNOWN
Classifier: Programming Language :: Python
Classifier: Programming Language :: Python :: 2
Classifier: Programming Language :: Python :: 2.7
Classifier: Programming Language :: Python :: 3
Classifier: Programming Language :: Python :: 3.5
Classifier: Programming Language :: Python :: 3.6
Classifier: Programming Language :: Python :: 3.7
Requires-Python: >=2.7, !=3.0.*, !=3.1.*, !=3.2.*, !=3.3.*, !=3.4.*
License-File: LICENSE
Requires-Dist: six (>=1.16.0)
